verbe_irreg/__init__.py
verbe_irreg/__main__.py
verbe_irreg/games_mode.py
verbe_irreg/load_list.py
verbe_irreg/data/liste_1.txt
verbe_irreg/data/liste_2.txt
verbe_irreg/data/liste_3.txt
verbe_irreg/data/liste_4.txt
verbe_irreg/data/liste_5.txt
verbe_irreg/data/liste_6.txt
verbe_irreg-1.6.0.dist-info/METADATA
verbe_irreg-1.6.0.dist-info/WHEEL
verbe_irreg-1.6.0.dist-info/entry_points.txt
verbe_irreg-1.6.0.dist-info/top_level.txt
verbe_irreg-1.6.0.dist-info/RECORD
