Metadata-Version: 2.1
Name: verbe-irreg
Version: 1.6.0
Summary: Programme de revision des verbe irregulier
Author-email: Timecraft122 <timecraft122@gmail.com>
Project-URL: Homepage, https://github.com/Timecraft122/Verbe-irregulier
Keywords: verbe_irregulier
Classifier: Programming Language :: Python :: 3
Requires-Python: >=3.0
